DIYables_MicroPython_Keypad/DIYables_MicroPython_Keypad.py
DIYables_MicroPython_Keypad/__init__.py
DIYables_MicroPython_Keypad-0.1.0.dist-info/LICENSE
DIYables_MicroPython_Keypad-0.1.0.dist-info/METADATA
DIYables_MicroPython_Keypad-0.1.0.dist-info/WHEEL
DIYables_MicroPython_Keypad-0.1.0.dist-info/top_level.txt
DIYables_MicroPython_Keypad-0.1.0.dist-info/RECORD
